Metadata-Version: 2.1
Name: ps3api
Version: 0.0.4
Summary: Python module for interacting with PS3 using CCAPI or TMAPI.
Home-page: https://github.com/iMoD1998/PS3API
Author: iMoD1998
Author-email: imod1998@protonmail.com
License: UNKNOWN
Project-URL: Bug Tracker, https://github.com/iMoD1998/PS3API/issues
Platform: UNKNOWN
Classifier: Programming Language :: Python :: 3
Classifier: Programming Language :: Assembly
Classifier: License :: OSI Approved :: MIT License
Classifier: Operating System :: Microsoft :: Windows
Classifier: Environment :: Win32 (MS Windows)
Classifier: Intended Audience :: Developers
Requires-Python: >=3.6
